day06/clk_50_10/clock_50_10.v
module clk_50_10(
	input clk,rst,
	output reg clk_out
);
reg [2:0] count;
always@(posedge clk or negedge rst)begin 
	if(!rst)begin
	count<=0;
	clk_out=0;
end
else if(count==3'b100)begin
		count <=0;
		clk_out = ~clk_out;
	end
	else
		count <= count+1;

end


endmodule

verilog/day06/clk_50_10_tb.v
module clk_50_10_tb;
reg clk,rst;
wire clk_out;
clk_50_10 clk_10(
	.clk(clk),
	.rst(rst),
	.clk_out(clk_out)
);
initial begin 
	$dumpfile("clk_10.vcd");
	$dumpvars(0,clk_50_10_tb);
end
initial clk = 0;
always #10 clk = ~clk;
initial begin 
	$monitor("clk=%b|rst=1||clk_out=%b",clk,rst,clk_out);
	rst =0;
	#25;
	rst=1;
	#500;
	$finish;
end
endmodule

verilog/day06/clk_10.vcd
$date
	Mon Aug  4 06:34:04 2025
$end
$version
	Icarus Verilog
$end
$timescale
	1s
$end
$scope module clk_50_10_tb $end
$var wire 1 ! clk_out $end
$var reg 1 " clk $end
$var reg 1 # rst $end
$scope module clk_10 $end
$var wire 1 " clk $end
$var wire 1 # rst $end
$var reg 1 ! clk_out $end
$var reg 3 $ count [2:0] $end
$upscope $end
$upscope $end
$enddefinitions $end
$comment Show the parameter values. $end
$dumpall
$end
#0
$dumpvars
b0 $
0#
0"
0!
$end
#10
1"
#20
0"
#25
1#
#30
b1 $
1"
#40
0"
#50
b10 $
1"
#60
0"
#70
b11 $
1"
#80
0"
#90
b100 $
1"
#100
0"
#110
b0 $
1!
1"
#120
0"
#130
b1 $
1"
#140
0"
#150
b10 $
1"
#160
0"
#170
b11 $
1"
#180
0"
#190
b100 $
1"
#200
0"
#210
b0 $
0!
1"
#220
0"
#230
b1 $
1"
#240
0"
#250
b10 $
1"
#260
0"
#270
b11 $
1"
#280
0"
#290
b100 $
1"
#300
0"
#310
b0 $
1!
1"
#320
0"
#330
b1 $
1"
#340
0"
#350
b10 $
1"
#360
0"
#370
b11 $
1"
#380
0"
#390
b100 $
1"
#400
0"
#410
b0 $
0!
1"
#420
0"
#430
b1 $
1"
#440
0"
#450
b10 $
1"
#460
0"
#470
b11 $
1"
#480
0"
#490
b100 $
1"
#500
0"
#510
b0 $
1!
1"
