registers/sipo_shift_reg/sipo_reg.v
module sipo(input clk,rst,serial_in,output reg [3:0]parallel_out);
always@(posedge clk )begin
	if(rst)
		parallel_out <= 4'b0000;
	else 
		parallel_out <= {parallel_out[2:0],serial_in}; //shift_left
		//parallel_out <= {serial_in,parallel_out[3:1]}; //shift_right
end
endmodule

registers/sipo_shift_reg/sipo_reg_tb.v
module sipo_tb;
reg clk,rst,serial_in;
wire[3:0] parallel_out;
sipo sipo_dut(.clk(clk),.rst(rst),.serial_in(serial_in),.parallel_out(parallel_out));
always #5 clk = ~clk;
initial begin
	$monitor("time = %0t | rst = %b | serial_in = %b | parallel_out = %b",$time,rst,serial_in,parallel_out);
	clk = 0;
	rst = 1;
	serial_in = 0;
	
	#10 rst = 0;

	#10 serial_in = 1;
	#10 serial_in = 0;
	#10 serial_in = 0;
	#10 serial_in = 1;

	#10 $finish;
end
initial begin
	$dumpfile("sipo.vcd");
	$dumpvars(0,sipo_tb);
end

endmodule

registers/sipo_shift_reg/sipo.vcd
$date
	Sat Dec 27 12:12:14 2025
$end
$version
	Icarus Verilog
$end
$timescale
	1s
$end
$scope module sipo_tb $end
$var wire 4 ! parallel_out [3:0] $end
$var reg 1 " clk $end
$var reg 1 # rst $end
$var reg 1 $ serial_in $end
$scope module sipo_dut $end
$var wire 1 " clk $end
$var wire 1 # rst $end
$var wire 1 $ serial_in $end
$var reg 4 % parallel_out [3:0] $end
$upscope $end
$upscope $end
$enddefinitions $end
$comment Show the parameter values. $end
$dumpall
$end
#0
$dumpvars
bx %
0$
1#
0"
bx !
$end
#5
b0 !
b0 %
1"
#10
0"
0#
#15
1"
#20
0"
1$
#25
b1 !
b1 %
1"
#30
0"
0$
#35
b10 !
b10 %
1"
#40
0"
#45
b100 !
b100 %
1"
#50
0"
1$
#55
b1001 !
b1001 %
1"
