flipflops_sync_async/d_flipflop/d_ff_rsts.v
module d_ff_rsts(input clk,rst,rst_n,d,output reg q);
always@(posedge clk or negedge rst_n)begin
	if(!rst_n)
		q <= 1'b0;
	else if(rst)
		q <= 1'b0;
	else
		q <= d;
end
endmodule

flipflops_sync_async/d_flipflop/d_ff_rsts_tb.v
module d_ff_rsts_tb;
reg clk,rst,rst_n,d;
wire q;
d_ff_rsts d_ff(.clk(clk),.rst(rst),.rst_n(rst_n),.d(d),.q(q));
always #5 clk = ~clk;
initial begin
	$monitor("time = %0t | clk = %b | rst = %b | rst_n = %b | d = %b | q = %b",$time,clk,rst,rst_n,d,q);
	clk = 0;
	rst =0;
	rst_n = 1;
	d = 1;
	#9 rst_n = 0;
	#8 rst_n = 1;
	#10 rst =1;
	#10 rst =0;
	#10 d = 0;
	#10 d =1;
	#20 $finish;
end
initial begin
       $dumpfile("d_ff_rst.vcd");	
	$dumpvars(0,d_ff_rsts_tb);
end
endmodule

flipflops_sync_async/d_flipflop/d_ff_rst.vcd
$date
	Sat Dec 27 07:28:40 2025
$end
$version
	Icarus Verilog
$end
$timescale
	1s
$end
$scope module d_ff_rsts_tb $end
$var wire 1 ! q $end
$var reg 1 " clk $end
$var reg 1 # d $end
$var reg 1 $ rst $end
$var reg 1 % rst_n $end
$scope module d_ff $end
$var wire 1 " clk $end
$var wire 1 # d $end
$var wire 1 $ rst $end
$var wire 1 % rst_n $end
$var reg 1 ! q $end
$upscope $end
$upscope $end
$enddefinitions $end
$comment Show the parameter values. $end
$dumpall
$end
#0
$dumpvars
1%
0$
1#
0"
x!
$end
#5
1!
1"
#9
0!
0%
#10
0"
#15
1"
#17
1%
#20
0"
#25
1!
1"
#27
1$
#30
0"
#35
0!
1"
#37
0$
#40
0"
#45
1!
1"
#47
0#
#50
0"
#55
0!
1"
#57
1#
#60
0"
#65
1!
1"
